[
  {
    "firstname": "Sheena",
    "lastname": "Duncan",
    "email": "sduncan0@nhs.uk"
  },
  {
    "firstname": "Davy",
    "lastname": "Kernes",
    "email": "dkernes1@springer.com"
  },
  {
    "firstname": "Herculie",
    "lastname": "Drayton",
    "email": "hdrayton2@fema.gov"
  },
  {
    "firstname": "Becki",
    "lastname": "Norvill",
    "email": "bnorvill3@shutterfly.com"
  },
  {
    "firstname": "Philip",
    "lastname": "Bon",
    "email": "pbon4@de.vu"
  },
  {
    "firstname": "Justis",
    "lastname": "Turle",
    "email": "jturle5@dmoz.org"
  },
  {
    "firstname": "Moss",
    "lastname": "Haldon",
    "email": "mhaldon6@huffingtonpost.com"
  },
  {
    "firstname": "Omero",
    "lastname": "Rowaszkiewicz",
    "email": "orowaszkiewicz7@usatoday.com"
  },
  {
    "firstname": "Natty",
    "lastname": "Heathwood",
    "email": "nheathwood8@people.com.cn"
  },
  {
    "firstname": "Nilson",
    "lastname": "Simmonite",
    "email": "nsimmonite9@youku.com"
  },
  {
    "firstname": "Itch",
    "lastname": "Charrisson",
    "email": "icharrissona@blinklist.com"
  },
  {
    "firstname": "Cart",
    "lastname": "Skews",
    "email": "cskewsb@wordpress.org"
  },
  {
    "firstname": "Webster",
    "lastname": "Brownsett",
    "email": "wbrownsettc@seesaa.net"
  },
  {
    "firstname": "Hazel",
    "lastname": "Peaker",
    "email": "hpeakerd@tamu.edu"
  },
  {
    "firstname": "Luther",
    "lastname": "Fenny",
    "email": "lfennye@google.nl"
  },
  {
    "firstname": "Phaidra",
    "lastname": "Brogden",
    "email": "pbrogdenf@uiuc.edu"
  },
  {
    "firstname": "Aristotle",
    "lastname": "Carnegie",
    "email": "acarnegieg@people.com.cn"
  },
  {
    "firstname": "Lenci",
    "lastname": "Abson",
    "email": "labsonh@nyu.edu"
  },
  {
    "firstname": "Merline",
    "lastname": "Croughan",
    "email": "mcroughani@auda.org.au"
  },
  {
    "firstname": "Roch",
    "lastname": "Riping",
    "email": "rripingj@discovery.com"
  },
  {
    "firstname": "Devlin",
    "lastname": "Pomeroy",
    "email": "dpomeroyk@omniture.com"
  },
  {
    "firstname": "Barty",
    "lastname": "Stove",
    "email": "bstovel@indiegogo.com"
  },
  {
    "firstname": "Dorey",
    "lastname": "Sewley",
    "email": "dsewleym@apple.com"
  },
  {
    "firstname": "Fairleigh",
    "lastname": "Clail",
    "email": "fclailn@constantcontact.com"
  },
  {
    "firstname": "Manuel",
    "lastname": "Sabater",
    "email": "msabatero@facebook.com"
  },
  {
    "firstname": "Chet",
    "lastname": "Hellsdon",
    "email": "chellsdonp@instagram.com"
  },
  {
    "firstname": "Roman",
    "lastname": "Hewes",
    "email": "rhewesq@blogspot.com"
  },
  {
    "firstname": "Courtney",
    "lastname": "Zanioletti",
    "email": "czaniolettir@oaic.gov.au"
  },
  {
    "firstname": "Malynda",
    "lastname": "Antonucci",
    "email": "mantonuccis@slashdot.org"
  },
  {
    "firstname": "Reggy",
    "lastname": "Growcock",
    "email": "rgrowcockt@twitpic.com"
  },
  {
    "firstname": "Jennie",
    "lastname": "Strapp",
    "email": "jstrappu@intel.com"
  },
  {
    "firstname": "Howey",
    "lastname": "Keppel",
    "email": "hkeppelv@furl.net"
  },
  {
    "firstname": "Berkeley",
    "lastname": "Longford",
    "email": "blongfordw@reference.com"
  },
  {
    "firstname": "Caddric",
    "lastname": "Ben-Aharon",
    "email": "cbenaharonx@theglobeandmail.com"
  },
  {
    "firstname": "Buddie",
    "lastname": "Vial",
    "email": "bvialy@princeton.edu"
  },
  {
    "firstname": "Maurizio",
    "lastname": "Frankish",
    "email": "mfrankishz@ifeng.com"
  },
  {
    "firstname": "Sydney",
    "lastname": "July",
    "email": "sjuly10@cpanel.net"
  },
  {
    "firstname": "Amata",
    "lastname": "Wakerley",
    "email": "awakerley11@freewebs.com"
  },
  {
    "firstname": "Connie",
    "lastname": "Mably",
    "email": "cmably12@phoca.cz"
  },
  {
    "firstname": "Cirstoforo",
    "lastname": "Sawkin",
    "email": "csawkin13@domainmarket.com"
  },
  {
    "firstname": "Rorie",
    "lastname": "Bullan",
    "email": "rbullan14@disqus.com"
  },
  {
    "firstname": "Guthrey",
    "lastname": "Pettman",
    "email": "gpettman15@amazon.co.uk"
  },
  {
    "firstname": "Calla",
    "lastname": "Bulgen",
    "email": "cbulgen16@usgs.gov"
  },
  {
    "firstname": "Briant",
    "lastname": "McVane",
    "email": "bmcvane17@salon.com"
  },
  {
    "firstname": "Phaidra",
    "lastname": "Hedan",
    "email": "phedan18@shutterfly.com"
  },
  {
    "firstname": "Nev",
    "lastname": "Chatelet",
    "email": "nchatelet19@wsj.com"
  },
  {
    "firstname": "Nerte",
    "lastname": "Taudevin",
    "email": "ntaudevin1a@xinhuanet.com"
  },
  {
    "firstname": "Ody",
    "lastname": "Goman",
    "email": "ogoman1b@yandex.ru"
  },
  {
    "firstname": "Marcela",
    "lastname": "Esherwood",
    "email": "mesherwood1c@webeden.co.uk"
  },
  {
    "firstname": "Hal",
    "lastname": "Bowering",
    "email": "hbowering1d@ycombinator.com"
  },
  {
    "firstname": "Billi",
    "lastname": "Freake",
    "email": "bfreake1e@abc.net.au"
  },
  {
    "firstname": "Phip",
    "lastname": "Whimper",
    "email": "pwhimper1f@cocolog-nifty.com"
  },
  {
    "firstname": "Gaultiero",
    "lastname": "Marsie",
    "email": "gmarsie1g@1und1.de"
  },
  {
    "firstname": "Odo",
    "lastname": "Claremont",
    "email": "oclaremont1h@mysql.com"
  },
  {
    "firstname": "Sigismund",
    "lastname": "Scarrott",
    "email": "sscarrott1i@mtv.com"
  },
  {
    "firstname": "Alyssa",
    "lastname": "Loade",
    "email": "aloade1j@sitemeter.com"
  },
  {
    "firstname": "Derk",
    "lastname": "Dutson",
    "email": "ddutson1k@hc360.com"
  },
  {
    "firstname": "Nellie",
    "lastname": "Rawkesby",
    "email": "nrawkesby1l@latimes.com"
  },
  {
    "firstname": "Dougy",
    "lastname": "Smithyman",
    "email": "dsmithyman1m@liveinternet.ru"
  },
  {
    "firstname": "Jose",
    "lastname": "Grishmanov",
    "email": "jgrishmanov1n@seesaa.net"
  },
  {
    "firstname": "Jessamine",
    "lastname": "Pactat",
    "email": "jpactat1o@barnesandnoble.com"
  },
  {
    "firstname": "Jody",
    "lastname": "Ziemsen",
    "email": "jziemsen1p@hexun.com"
  },
  {
    "firstname": "Kath",
    "lastname": "Bontein",
    "email": "kbontein1q@who.int"
  },
  {
    "firstname": "Tandi",
    "lastname": "De Lasci",
    "email": "tdelasci1r@dyndns.org"
  },
  {
    "firstname": "Wilhelm",
    "lastname": "Upshall",
    "email": "wupshall1s@tripod.com"
  },
  {
    "firstname": "Haven",
    "lastname": "Vlasyuk",
    "email": "hvlasyuk1t@rediff.com"
  },
  {
    "firstname": "Verne",
    "lastname": "Speare",
    "email": "vspeare1u@rakuten.co.jp"
  },
  {
    "firstname": "Leonelle",
    "lastname": "Denziloe",
    "email": "ldenziloe1v@soundcloud.com"
  },
  {
    "firstname": "Dolph",
    "lastname": "McBratney",
    "email": "dmcbratney1w@miitbeian.gov.cn"
  },
  {
    "firstname": "Celene",
    "lastname": "O'Henery",
    "email": "cohenery1x@goo.gl"
  },
  {
    "firstname": "Julietta",
    "lastname": "Tidman",
    "email": "jtidman1y@salon.com"
  },
  {
    "firstname": "Rawley",
    "lastname": "Sam",
    "email": "rsam1z@wikispaces.com"
  },
  {
    "firstname": "Trey",
    "lastname": "Fyers",
    "email": "tfyers20@arizona.edu"
  },
  {
    "firstname": "Kevin",
    "lastname": "Giacobelli",
    "email": "kgiacobelli21@e-recht24.de"
  },
  {
    "firstname": "Zed",
    "lastname": "Adnams",
    "email": "zadnams22@godaddy.com"
  },
  {
    "firstname": "Ines",
    "lastname": "Kuhnel",
    "email": "ikuhnel23@mayoclinic.com"
  },
  {
    "firstname": "Emmalynne",
    "lastname": "Lemery",
    "email": "elemery24@newsvine.com"
  },
  {
    "firstname": "Alida",
    "lastname": "Labba",
    "email": "alabba25@msn.com"
  },
  {
    "firstname": "Tallulah",
    "lastname": "Cluet",
    "email": "tcluet26@ed.gov"
  },
  {
    "firstname": "Tanitansy",
    "lastname": "Haggidon",
    "email": "thaggidon27@google.com.hk"
  },
  {
    "firstname": "Caria",
    "lastname": "Gethins",
    "email": "cgethins28@geocities.com"
  },
  {
    "firstname": "Raffarty",
    "lastname": "Fettis",
    "email": "rfettis29@ustream.tv"
  },
  {
    "firstname": "Kitti",
    "lastname": "Remmers",
    "email": "kremmers2a@ca.gov"
  },
  {
    "firstname": "Karim",
    "lastname": "MacArd",
    "email": "kmacard2b@independent.co.uk"
  },
  {
    "firstname": "Barbabra",
    "lastname": "Rubinovitsch",
    "email": "brubinovitsch2c@wikimedia.org"
  },
  {
    "firstname": "Morrie",
    "lastname": "Comar",
    "email": "mcomar2d@nymag.com"
  },
  {
    "firstname": "Gwen",
    "lastname": "Parlot",
    "email": "gparlot2e@topsy.com"
  },
  {
    "firstname": "Avram",
    "lastname": "L'Episcopi",
    "email": "alepiscopi2f@imgur.com"
  },
  {
    "firstname": "Kelci",
    "lastname": "Brazelton",
    "email": "kbrazelton2g@facebook.com"
  },
  {
    "firstname": "Jeffie",
    "lastname": "Casseldine",
    "email": "jcasseldine2h@com.com"
  },
  {
    "firstname": "Elden",
    "lastname": "Sandeford",
    "email": "esandeford2i@ycombinator.com"
  },
  {
    "firstname": "Wylma",
    "lastname": "Mardle",
    "email": "wmardle2j@ihg.com"
  },
  {
    "firstname": "Regan",
    "lastname": "Odeson",
    "email": "rodeson2k@squidoo.com"
  },
  {
    "firstname": "Erick",
    "lastname": "Donkersley",
    "email": "edonkersley2l@uol.com.br"
  },
  {
    "firstname": "Marianne",
    "lastname": "Calf",
    "email": "mcalf2m@umich.edu"
  },
  {
    "firstname": "Thekla",
    "lastname": "Jenton",
    "email": "tjenton2n@sfgate.com"
  },
  {
    "firstname": "Jarrett",
    "lastname": "Spiers",
    "email": "jspiers2o@so-net.ne.jp"
  },
  {
    "firstname": "Darrelle",
    "lastname": "Fockes",
    "email": "dfockes2p@wikia.com"
  },
  {
    "firstname": "Son",
    "lastname": "Huggon",
    "email": "shuggon2q@oracle.com"
  },
  {
    "firstname": "Tanya",
    "lastname": "Bes",
    "email": "tbes2r@google.co.uk"
  },
  {
    "firstname": "Camey",
    "lastname": "Face",
    "email": "cface2s@paypal.com"
  },
  {
    "firstname": "Pierrette",
    "lastname": "Oret",
    "email": "poret2t@economist.com"
  },
  {
    "firstname": "Coop",
    "lastname": "Gunner",
    "email": "cgunner2u@hhs.gov"
  },
  {
    "firstname": "Derry",
    "lastname": "Tunstall",
    "email": "dtunstall2v@baidu.com"
  },
  {
    "firstname": "Odell",
    "lastname": "Alton",
    "email": "oalton2w@livejournal.com"
  },
  {
    "firstname": "Al",
    "lastname": "Davisson",
    "email": "adavisson2x@deviantart.com"
  },
  {
    "firstname": "Bordie",
    "lastname": "Pead",
    "email": "bpead2y@icq.com"
  },
  {
    "firstname": "Stavros",
    "lastname": "Sewell",
    "email": "ssewell2z@nytimes.com"
  },
  {
    "firstname": "Aurelie",
    "lastname": "McGawn",
    "email": "amcgawn30@wisc.edu"
  },
  {
    "firstname": "Harley",
    "lastname": "Noe",
    "email": "hnoe31@delicious.com"
  },
  {
    "firstname": "Padget",
    "lastname": "Venditti",
    "email": "pvenditti32@time.com"
  },
  {
    "firstname": "Pierette",
    "lastname": "Prevett",
    "email": "pprevett33@marketwatch.com"
  },
  {
    "firstname": "Mandi",
    "lastname": "Fludder",
    "email": "mfludder34@nymag.com"
  },
  {
    "firstname": "Terese",
    "lastname": "Testin",
    "email": "ttestin35@gizmodo.com"
  },
  {
    "firstname": "Faulkner",
    "lastname": "Chester",
    "email": "fchester36@weibo.com"
  },
  {
    "firstname": "Becki",
    "lastname": "Troctor",
    "email": "btroctor37@home.pl"
  },
  {
    "firstname": "Mathian",
    "lastname": "Lechmere",
    "email": "mlechmere38@amazon.co.uk"
  },
  {
    "firstname": "Nobe",
    "lastname": "Gonzalo",
    "email": "ngonzalo39@china.com.cn"
  },
  {
    "firstname": "Bride",
    "lastname": "Klageman",
    "email": "bklageman3a@imdb.com"
  },
  {
    "firstname": "Viviene",
    "lastname": "Vautre",
    "email": "vvautre3b@weibo.com"
  },
  {
    "firstname": "Mair",
    "lastname": "Fowler",
    "email": "mfowler3c@yandex.ru"
  },
  {
    "firstname": "Bethena",
    "lastname": "Marusyak",
    "email": "bmarusyak3d@linkedin.com"
  },
  {
    "firstname": "Adelaide",
    "lastname": "Didsbury",
    "email": "adidsbury3e@amazonaws.com"
  },
  {
    "firstname": "Kristine",
    "lastname": "Grishankov",
    "email": "kgrishankov3f@businesswire.com"
  },
  {
    "firstname": "Dale",
    "lastname": "Walthew",
    "email": "dwalthew3g@ucsd.edu"
  },
  {
    "firstname": "Clareta",
    "lastname": "Yven",
    "email": "cyven3h@reddit.com"
  },
  {
    "firstname": "Emmalynne",
    "lastname": "Winscum",
    "email": "ewinscum3i@pagesperso-orange.fr"
  },
  {
    "firstname": "Remington",
    "lastname": "Kirkham",
    "email": "rkirkham3j@ft.com"
  },
  {
    "firstname": "Odilia",
    "lastname": "Givens",
    "email": "ogivens3k@twitpic.com"
  },
  {
    "firstname": "Rafaelita",
    "lastname": "Saltrese",
    "email": "rsaltrese3l@nifty.com"
  },
  {
    "firstname": "Reg",
    "lastname": "Gurdon",
    "email": "rgurdon3m@wikimedia.org"
  },
  {
    "firstname": "Tommi",
    "lastname": "Clyburn",
    "email": "tclyburn3n@umich.edu"
  },
  {
    "firstname": "Zonnya",
    "lastname": "Lascell",
    "email": "zlascell3o@rediff.com"
  },
  {
    "firstname": "Agna",
    "lastname": "Skule",
    "email": "askule3p@canalblog.com"
  },
  {
    "firstname": "Richart",
    "lastname": "Shafto",
    "email": "rshafto3q@cbsnews.com"
  },
  {
    "firstname": "Sherill",
    "lastname": "Cappel",
    "email": "scappel3r@epa.gov"
  },
  {
    "firstname": "Malva",
    "lastname": "McQuin",
    "email": "mmcquin3s@businesswire.com"
  },
  {
    "firstname": "Daniella",
    "lastname": "Stiegars",
    "email": "dstiegars3t@amazon.co.jp"
  },
  {
    "firstname": "Ardelis",
    "lastname": "Pozzo",
    "email": "apozzo3u@examiner.com"
  },
  {
    "firstname": "Evangeline",
    "lastname": "Tenney",
    "email": "etenney3v@economist.com"
  },
  {
    "firstname": "Kaia",
    "lastname": "Dyhouse",
    "email": "kdyhouse3w@nifty.com"
  },
  {
    "firstname": "Gloria",
    "lastname": "Dewes",
    "email": "gdewes3x@livejournal.com"
  },
  {
    "firstname": "Andriana",
    "lastname": "Bridgewood",
    "email": "abridgewood3y@sourceforge.net"
  },
  {
    "firstname": "Alexei",
    "lastname": "Dewi",
    "email": "adewi3z@multiply.com"
  },
  {
    "firstname": "Margo",
    "lastname": "Gunthorp",
    "email": "mgunthorp40@hibu.com"
  },
  {
    "firstname": "Angy",
    "lastname": "Cram",
    "email": "acram41@over-blog.com"
  },
  {
    "firstname": "Maurits",
    "lastname": "Stroband",
    "email": "mstroband42@devhub.com"
  },
  {
    "firstname": "Mellie",
    "lastname": "Edon",
    "email": "medon43@businesswire.com"
  },
  {
    "firstname": "Edithe",
    "lastname": "Sigge",
    "email": "esigge44@oracle.com"
  },
  {
    "firstname": "Dierdre",
    "lastname": "McElree",
    "email": "dmcelree45@issuu.com"
  },
  {
    "firstname": "Brit",
    "lastname": "Dodge",
    "email": "bdodge46@51.la"
  },
  {
    "firstname": "Whitman",
    "lastname": "Rossant",
    "email": "wrossant47@qq.com"
  },
  {
    "firstname": "Sheeree",
    "lastname": "Stanbridge",
    "email": "sstanbridge48@ask.com"
  },
  {
    "firstname": "Hyacinthie",
    "lastname": "Baldin",
    "email": "hbaldin49@addtoany.com"
  },
  {
    "firstname": "Adaline",
    "lastname": "Foale",
    "email": "afoale4a@sun.com"
  },
  {
    "firstname": "Farand",
    "lastname": "Cramond",
    "email": "fcramond4b@multiply.com"
  },
  {
    "firstname": "Teresina",
    "lastname": "Albrighton",
    "email": "talbrighton4c@pen.io"
  },
  {
    "firstname": "Nanice",
    "lastname": "Shenfish",
    "email": "nshenfish4d@oaic.gov.au"
  },
  {
    "firstname": "Edee",
    "lastname": "Kirrage",
    "email": "ekirrage4e@arizona.edu"
  },
  {
    "firstname": "Sallie",
    "lastname": "Haverty",
    "email": "shaverty4f@nytimes.com"
  },
  {
    "firstname": "Titos",
    "lastname": "Cecchi",
    "email": "tcecchi4g@si.edu"
  },
  {
    "firstname": "Rogers",
    "lastname": "Lobe",
    "email": "rlobe4h@sohu.com"
  },
  {
    "firstname": "Dorey",
    "lastname": "Trimming",
    "email": "dtrimming4i@google.cn"
  },
  {
    "firstname": "Angela",
    "lastname": "Halton",
    "email": "ahalton4j@goodreads.com"
  },
  {
    "firstname": "Norbert",
    "lastname": "Gresswood",
    "email": "ngresswood4k@sciencedaily.com"
  },
  {
    "firstname": "Felice",
    "lastname": "Matuszyk",
    "email": "fmatuszyk4l@artisteer.com"
  },
  {
    "firstname": "Kinnie",
    "lastname": "Letteresse",
    "email": "kletteresse4m@forbes.com"
  },
  {
    "firstname": "Pia",
    "lastname": "Holworth",
    "email": "pholworth4n@mit.edu"
  },
  {
    "firstname": "Latisha",
    "lastname": "Fitzpayn",
    "email": "lfitzpayn4o@t.co"
  },
  {
    "firstname": "Hercules",
    "lastname": "Everington",
    "email": "heverington4p@1688.com"
  },
  {
    "firstname": "Katrine",
    "lastname": "Juste",
    "email": "kjuste4q@soup.io"
  },
  {
    "firstname": "Koenraad",
    "lastname": "Gyorgy",
    "email": "kgyorgy4r@squarespace.com"
  },
  {
    "firstname": "Tess",
    "lastname": "Brigge",
    "email": "tbrigge4s@cpanel.net"
  },
  {
    "firstname": "Binnie",
    "lastname": "Hallwood",
    "email": "bhallwood4t@a8.net"
  },
  {
    "firstname": "Orran",
    "lastname": "Baker",
    "email": "obaker4u@de.vu"
  },
  {
    "firstname": "Leonora",
    "lastname": "Crick",
    "email": "lcrick4v@cbslocal.com"
  },
  {
    "firstname": "Lotte",
    "lastname": "Fleury",
    "email": "lfleury4w@google.co.jp"
  },
  {
    "firstname": "Pippa",
    "lastname": "Klawi",
    "email": "pklawi4x@networksolutions.com"
  },
  {
    "firstname": "Mady",
    "lastname": "Bazylets",
    "email": "mbazylets4y@pcworld.com"
  },
  {
    "firstname": "Mickie",
    "lastname": "Hatley",
    "email": "mhatley4z@prnewswire.com"
  },
  {
    "firstname": "Mufi",
    "lastname": "Powelee",
    "email": "mpowelee50@shinystat.com"
  },
  {
    "firstname": "Gale",
    "lastname": "Delacour",
    "email": "gdelacour51@seesaa.net"
  },
  {
    "firstname": "Bernarr",
    "lastname": "Albrecht",
    "email": "balbrecht52@de.vu"
  },
  {
    "firstname": "Oneida",
    "lastname": "Duffrie",
    "email": "oduffrie53@tripadvisor.com"
  },
  {
    "firstname": "Daile",
    "lastname": "Nairy",
    "email": "dnairy54@vkontakte.ru"
  },
  {
    "firstname": "Del",
    "lastname": "Jouaneton",
    "email": "djouaneton55@blog.com"
  },
  {
    "firstname": "Colby",
    "lastname": "Sommers",
    "email": "csommers56@spotify.com"
  },
  {
    "firstname": "Lorain",
    "lastname": "McElwee",
    "email": "lmcelwee57@webmd.com"
  },
  {
    "firstname": "Freddi",
    "lastname": "Effemy",
    "email": "feffemy58@shop-pro.jp"
  },
  {
    "firstname": "Ulrike",
    "lastname": "Tiery",
    "email": "utiery59@list-manage.com"
  },
  {
    "firstname": "Grethel",
    "lastname": "McKnockiter",
    "email": "gmcknockiter5a@cornell.edu"
  },
  {
    "firstname": "Valle",
    "lastname": "MacNamee",
    "email": "vmacnamee5b@icio.us"
  },
  {
    "firstname": "Cecil",
    "lastname": "Alesio",
    "email": "calesio5c@princeton.edu"
  },
  {
    "firstname": "Gasper",
    "lastname": "Acarson",
    "email": "gacarson5d@unesco.org"
  },
  {
    "firstname": "Jarrod",
    "lastname": "Copner",
    "email": "jcopner5e@home.pl"
  },
  {
    "firstname": "Livvie",
    "lastname": "Propper",
    "email": "lpropper5f@whitehouse.gov"
  },
  {
    "firstname": "Krystle",
    "lastname": "Shorey",
    "email": "kshorey5g@sun.com"
  },
  {
    "firstname": "Aldo",
    "lastname": "Blenkharn",
    "email": "ablenkharn5h@hud.gov"
  },
  {
    "firstname": "Randy",
    "lastname": "Goldthorp",
    "email": "rgoldthorp5i@java.com"
  },
  {
    "firstname": "Gael",
    "lastname": "Turneux",
    "email": "gturneux5j@edublogs.org"
  },
  {
    "firstname": "Breanne",
    "lastname": "Catton",
    "email": "bcatton5k@guardian.co.uk"
  },
  {
    "firstname": "Annabal",
    "lastname": "Halse",
    "email": "ahalse5l@canalblog.com"
  },
  {
    "firstname": "Lani",
    "lastname": "Bendson",
    "email": "lbendson5m@liveinternet.ru"
  },
  {
    "firstname": "Krystalle",
    "lastname": "Reddan",
    "email": "kreddan5n@google.co.uk"
  },
  {
    "firstname": "Pippa",
    "lastname": "Littlewood",
    "email": "plittlewood5o@pbs.org"
  },
  {
    "firstname": "Arly",
    "lastname": "Crut",
    "email": "acrut5p@goo.ne.jp"
  },
  {
    "firstname": "Erl",
    "lastname": "Stiven",
    "email": "estiven5q@adobe.com"
  },
  {
    "firstname": "Clary",
    "lastname": "Somerset",
    "email": "csomerset5r@drupal.org"
  },
  {
    "firstname": "Gerry",
    "lastname": "Hilary",
    "email": "ghilary5s@discuz.net"
  },
  {
    "firstname": "Wain",
    "lastname": "Couth",
    "email": "wcouth5t@sina.com.cn"
  },
  {
    "firstname": "Gustavus",
    "lastname": "Swenson",
    "email": "gswenson5u@technorati.com"
  },
  {
    "firstname": "Kevina",
    "lastname": "Domino",
    "email": "kdomino5v@instagram.com"
  },
  {
    "firstname": "Alessandra",
    "lastname": "Spring",
    "email": "aspring5w@aol.com"
  },
  {
    "firstname": "Hollyanne",
    "lastname": "Harlick",
    "email": "hharlick5x@meetup.com"
  },
  {
    "firstname": "Cobbie",
    "lastname": "Gallacher",
    "email": "cgallacher5y@usgs.gov"
  },
  {
    "firstname": "Donielle",
    "lastname": "Woolf",
    "email": "dwoolf5z@fema.gov"
  },
  {
    "firstname": "Iseabal",
    "lastname": "Santore",
    "email": "isantore60@yolasite.com"
  },
  {
    "firstname": "Arabel",
    "lastname": "Igounet",
    "email": "aigounet61@printfriendly.com"
  },
  {
    "firstname": "Harv",
    "lastname": "Morot",
    "email": "hmorot62@google.cn"
  },
  {
    "firstname": "Harlan",
    "lastname": "Elwood",
    "email": "helwood63@ft.com"
  },
  {
    "firstname": "Haze",
    "lastname": "Whewill",
    "email": "hwhewill64@meetup.com"
  },
  {
    "firstname": "Boothe",
    "lastname": "Domone",
    "email": "bdomone65@cdbaby.com"
  },
  {
    "firstname": "Berti",
    "lastname": "Dymidowski",
    "email": "bdymidowski66@soundcloud.com"
  },
  {
    "firstname": "Stormi",
    "lastname": "Yurinov",
    "email": "syurinov67@epa.gov"
  },
  {
    "firstname": "Finn",
    "lastname": "Seward",
    "email": "fseward68@mysql.com"
  },
  {
    "firstname": "Quintilla",
    "lastname": "Caldairou",
    "email": "qcaldairou69@businessinsider.com"
  },
  {
    "firstname": "Seumas",
    "lastname": "Pankhurst.",
    "email": "spankhurst6a@ning.com"
  },
  {
    "firstname": "Cary",
    "lastname": "Elies",
    "email": "celies6b@timesonline.co.uk"
  },
  {
    "firstname": "Amberly",
    "lastname": "Summerton",
    "email": "asummerton6c@free.fr"
  },
  {
    "firstname": "Merrick",
    "lastname": "Petyanin",
    "email": "mpetyanin6d@tuttocitta.it"
  },
  {
    "firstname": "Karmen",
    "lastname": "McClenaghan",
    "email": "kmcclenaghan6e@businesswire.com"
  },
  {
    "firstname": "Dennis",
    "lastname": "Bougen",
    "email": "dbougen6f@zdnet.com"
  },
  {
    "firstname": "Loni",
    "lastname": "Genery",
    "email": "lgenery6g@yellowpages.com"
  },
  {
    "firstname": "Marty",
    "lastname": "Bayle",
    "email": "mbayle6h@simplemachines.org"
  },
  {
    "firstname": "Orsa",
    "lastname": "Seater",
    "email": "oseater6i@yolasite.com"
  },
  {
    "firstname": "Kaylil",
    "lastname": "Ratke",
    "email": "kratke6j@bloglovin.com"
  },
  {
    "firstname": "Karee",
    "lastname": "Kurtis",
    "email": "kkurtis6k@ftc.gov"
  },
  {
    "firstname": "Harris",
    "lastname": "Stichall",
    "email": "hstichall6l@zdnet.com"
  },
  {
    "firstname": "Johann",
    "lastname": "Chasteney",
    "email": "jchasteney6m@purevolume.com"
  },
  {
    "firstname": "Jesselyn",
    "lastname": "Rosenstock",
    "email": "jrosenstock6n@nih.gov"
  },
  {
    "firstname": "Trish",
    "lastname": "Ibbs",
    "email": "tibbs6o@pen.io"
  },
  {
    "firstname": "Colet",
    "lastname": "Baudrey",
    "email": "cbaudrey6p@feedburner.com"
  },
  {
    "firstname": "Ayn",
    "lastname": "Lanegran",
    "email": "alanegran6q@delicious.com"
  },
  {
    "firstname": "Barnie",
    "lastname": "Caulcott",
    "email": "bcaulcott6r@netscape.com"
  },
  {
    "firstname": "Roxanne",
    "lastname": "Clampin",
    "email": "rclampin6s@sina.com.cn"
  },
  {
    "firstname": "Dermot",
    "lastname": "Spruce",
    "email": "dspruce6t@businessinsider.com"
  },
  {
    "firstname": "Constantin",
    "lastname": "Guitel",
    "email": "cguitel6u@wp.com"
  },
  {
    "firstname": "Georgena",
    "lastname": "Scotford",
    "email": "gscotford6v@cafepress.com"
  },
  {
    "firstname": "Bekki",
    "lastname": "Loges",
    "email": "bloges6w@naver.com"
  },
  {
    "firstname": "Victor",
    "lastname": "Heddon",
    "email": "vheddon6x@so-net.ne.jp"
  },
  {
    "firstname": "Concordia",
    "lastname": "O'Carney",
    "email": "cocarney6y@macromedia.com"
  },
  {
    "firstname": "Callean",
    "lastname": "Dunnan",
    "email": "cdunnan6z@delicious.com"
  },
  {
    "firstname": "Gretta",
    "lastname": "Kittel",
    "email": "gkittel70@qq.com"
  },
  {
    "firstname": "Lincoln",
    "lastname": "Ditchburn",
    "email": "lditchburn71@ft.com"
  },
  {
    "firstname": "Leonanie",
    "lastname": "Clemmitt",
    "email": "lclemmitt72@hp.com"
  },
  {
    "firstname": "Gallard",
    "lastname": "Bigglestone",
    "email": "gbigglestone73@zdnet.com"
  },
  {
    "firstname": "Yasmeen",
    "lastname": "Stainer",
    "email": "ystainer74@bluehost.com"
  },
  {
    "firstname": "Leelah",
    "lastname": "Pitney",
    "email": "lpitney75@xrea.com"
  },
  {
    "firstname": "Gerty",
    "lastname": "Avieson",
    "email": "gavieson76@g.co"
  },
  {
    "firstname": "Port",
    "lastname": "Bigg",
    "email": "pbigg77@posterous.com"
  },
  {
    "firstname": "Jorge",
    "lastname": "Stampe",
    "email": "jstampe78@slashdot.org"
  },
  {
    "firstname": "Briana",
    "lastname": "Kem",
    "email": "bkem79@canalblog.com"
  },
  {
    "firstname": "Victoir",
    "lastname": "Hevner",
    "email": "vhevner7a@google.co.uk"
  },
  {
    "firstname": "Alexandros",
    "lastname": "Alsobrook",
    "email": "aalsobrook7b@t.co"
  },
  {
    "firstname": "Tristam",
    "lastname": "Morrall",
    "email": "tmorrall7c@flickr.com"
  },
  {
    "firstname": "Obediah",
    "lastname": "Beckerleg",
    "email": "obeckerleg7d@unblog.fr"
  },
  {
    "firstname": "Nertie",
    "lastname": "Leppard",
    "email": "nleppard7e@csmonitor.com"
  },
  {
    "firstname": "Carey",
    "lastname": "Gherardelli",
    "email": "cgherardelli7f@slate.com"
  },
  {
    "firstname": "Lizzy",
    "lastname": "Longson",
    "email": "llongson7g@php.net"
  },
  {
    "firstname": "Maible",
    "lastname": "Bendin",
    "email": "mbendin7h@unesco.org"
  },
  {
    "firstname": "Darn",
    "lastname": "Cathenod",
    "email": "dcathenod7i@wiley.com"
  },
  {
    "firstname": "Creight",
    "lastname": "Quarton",
    "email": "cquarton7j@diigo.com"
  },
  {
    "firstname": "Netta",
    "lastname": "Rackley",
    "email": "nrackley7k@51.la"
  },
  {
    "firstname": "Zachery",
    "lastname": "Abramow",
    "email": "zabramow7l@wsj.com"
  },
  {
    "firstname": "Brooke",
    "lastname": "Mottini",
    "email": "bmottini7m@ft.com"
  },
  {
    "firstname": "Kizzee",
    "lastname": "Scutts",
    "email": "kscutts7n@baidu.com"
  },
  {
    "firstname": "Tiphani",
    "lastname": "McGrirl",
    "email": "tmcgrirl7o@odnoklassniki.ru"
  },
  {
    "firstname": "Erinn",
    "lastname": "Emeline",
    "email": "eemeline7p@apache.org"
  },
  {
    "firstname": "Grace",
    "lastname": "Balf",
    "email": "gbalf7q@paypal.com"
  },
  {
    "firstname": "Carlotta",
    "lastname": "Franscioni",
    "email": "cfranscioni7r@godaddy.com"
  },
  {
    "firstname": "Oswell",
    "lastname": "Janicijevic",
    "email": "ojanicijevic7s@diigo.com"
  },
  {
    "firstname": "Sophronia",
    "lastname": "Bernet",
    "email": "sbernet7t@mozilla.com"
  },
  {
    "firstname": "York",
    "lastname": "Pencot",
    "email": "ypencot7u@google.com.br"
  },
  {
    "firstname": "Gena",
    "lastname": "Wrassell",
    "email": "gwrassell7v@friendfeed.com"
  },
  {
    "firstname": "Herschel",
    "lastname": "Bebbington",
    "email": "hbebbington7w@acquirethisname.com"
  },
  {
    "firstname": "Carlos",
    "lastname": "Fireman",
    "email": "cfireman7x@constantcontact.com"
  },
  {
    "firstname": "Esther",
    "lastname": "Norway",
    "email": "enorway7y@answers.com"
  },
  {
    "firstname": "Shae",
    "lastname": "Latty",
    "email": "slatty7z@google.com.br"
  },
  {
    "firstname": "Maxy",
    "lastname": "Skaif",
    "email": "mskaif80@opera.com"
  },
  {
    "firstname": "Charyl",
    "lastname": "Pegg",
    "email": "cpegg81@tripadvisor.com"
  },
  {
    "firstname": "Alwyn",
    "lastname": "Falkingham",
    "email": "afalkingham82@rakuten.co.jp"
  },
  {
    "firstname": "Fran",
    "lastname": "Hanselman",
    "email": "fhanselman83@marketwatch.com"
  },
  {
    "firstname": "Barty",
    "lastname": "Gillford",
    "email": "bgillford84@nymag.com"
  },
  {
    "firstname": "Galen",
    "lastname": "Gregoletti",
    "email": "ggregoletti85@facebook.com"
  },
  {
    "firstname": "Raynard",
    "lastname": "Attac",
    "email": "rattac86@free.fr"
  },
  {
    "firstname": "Jefferey",
    "lastname": "Keilty",
    "email": "jkeilty87@illinois.edu"
  },
  {
    "firstname": "Courtney",
    "lastname": "Antoszewski",
    "email": "cantoszewski88@theguardian.com"
  },
  {
    "firstname": "Jodie",
    "lastname": "Maven",
    "email": "jmaven89@europa.eu"
  },
  {
    "firstname": "Jess",
    "lastname": "Lafranconi",
    "email": "jlafranconi8a@vimeo.com"
  },
  {
    "firstname": "Yorgos",
    "lastname": "Wadeling",
    "email": "ywadeling8b@eventbrite.com"
  },
  {
    "firstname": "Vilhelmina",
    "lastname": "Muirhead",
    "email": "vmuirhead8c@weibo.com"
  },
  {
    "firstname": "Ellswerth",
    "lastname": "Yellowlees",
    "email": "eyellowlees8d@ebay.com"
  },
  {
    "firstname": "Cleavland",
    "lastname": "Gosson",
    "email": "cgosson8e@boston.com"
  },
  {
    "firstname": "Kory",
    "lastname": "Secrett",
    "email": "ksecrett8f@reverbnation.com"
  },
  {
    "firstname": "Idell",
    "lastname": "Blankman",
    "email": "iblankman8g@miibeian.gov.cn"
  },
  {
    "firstname": "Carree",
    "lastname": "Gorstidge",
    "email": "cgorstidge8h@elegantthemes.com"
  },
  {
    "firstname": "Spike",
    "lastname": "Guillart",
    "email": "sguillart8i@msn.com"
  },
  {
    "firstname": "Feodora",
    "lastname": "Haggus",
    "email": "fhaggus8j@amazon.co.jp"
  },
  {
    "firstname": "Sheridan",
    "lastname": "Baillie",
    "email": "sbaillie8k@joomla.org"
  },
  {
    "firstname": "Raphael",
    "lastname": "Conville",
    "email": "rconville8l@about.me"
  },
  {
    "firstname": "Farlie",
    "lastname": "Chupin",
    "email": "fchupin8m@qq.com"
  },
  {
    "firstname": "Emmi",
    "lastname": "Sowte",
    "email": "esowte8n@mayoclinic.com"
  },
  {
    "firstname": "Teddie",
    "lastname": "Alflat",
    "email": "talflat8o@amazonaws.com"
  },
  {
    "firstname": "Cortney",
    "lastname": "Methringham",
    "email": "cmethringham8p@furl.net"
  },
  {
    "firstname": "Georgina",
    "lastname": "Olekhov",
    "email": "golekhov8q@sakura.ne.jp"
  },
  {
    "firstname": "Howard",
    "lastname": "Wanklin",
    "email": "hwanklin8r@weebly.com"
  },
  {
    "firstname": "Willamina",
    "lastname": "Pentecust",
    "email": "wpentecust8s@marriott.com"
  },
  {
    "firstname": "Kate",
    "lastname": "Goundsy",
    "email": "kgoundsy8t@jigsy.com"
  },
  {
    "firstname": "Basile",
    "lastname": "Ottam",
    "email": "bottam8u@toplist.cz"
  },
  {
    "firstname": "Brewer",
    "lastname": "Spriggin",
    "email": "bspriggin8v@illinois.edu"
  },
  {
    "firstname": "Marcelline",
    "lastname": "Beadel",
    "email": "mbeadel8w@about.com"
  },
  {
    "firstname": "Wylma",
    "lastname": "Dumphrey",
    "email": "wdumphrey8x@symantec.com"
  },
  {
    "firstname": "Lesly",
    "lastname": "Hardacre",
    "email": "lhardacre8y@etsy.com"
  },
  {
    "firstname": "Allissa",
    "lastname": "Errey",
    "email": "aerrey8z@time.com"
  },
  {
    "firstname": "Almeria",
    "lastname": "Jakubowsky",
    "email": "ajakubowsky90@alexa.com"
  },
  {
    "firstname": "Gradey",
    "lastname": "Warbys",
    "email": "gwarbys91@weebly.com"
  },
  {
    "firstname": "Debby",
    "lastname": "Janczyk",
    "email": "djanczyk92@ted.com"
  },
  {
    "firstname": "Hamnet",
    "lastname": "O'Conor",
    "email": "hoconor93@biglobe.ne.jp"
  },
  {
    "firstname": "Ive",
    "lastname": "Papps",
    "email": "ipapps94@marketwatch.com"
  },
  {
    "firstname": "Avis",
    "lastname": "Pappi",
    "email": "apappi95@nhs.uk"
  },
  {
    "firstname": "Babb",
    "lastname": "Grigoriev",
    "email": "bgrigoriev96@ehow.com"
  },
  {
    "firstname": "Maryellen",
    "lastname": "Whitton",
    "email": "mwhitton97@hao123.com"
  },
  {
    "firstname": "Steve",
    "lastname": "Drabble",
    "email": "sdrabble98@ifeng.com"
  },
  {
    "firstname": "Dita",
    "lastname": "Blackboro",
    "email": "dblackboro99@ovh.net"
  },
  {
    "firstname": "Quincey",
    "lastname": "Money",
    "email": "qmoney9a@netscape.com"
  },
  {
    "firstname": "Hildegarde",
    "lastname": "Rathborne",
    "email": "hrathborne9b@indiatimes.com"
  },
  {
    "firstname": "Neale",
    "lastname": "Davenall",
    "email": "ndavenall9c@shutterfly.com"
  },
  {
    "firstname": "Petronella",
    "lastname": "Rountree",
    "email": "prountree9d@icq.com"
  },
  {
    "firstname": "Marten",
    "lastname": "Emig",
    "email": "memig9e@baidu.com"
  },
  {
    "firstname": "Shawn",
    "lastname": "Gillitt",
    "email": "sgillitt9f@apple.com"
  },
  {
    "firstname": "Beverly",
    "lastname": "Washbrook",
    "email": "bwashbrook9g@histats.com"
  },
  {
    "firstname": "Maud",
    "lastname": "Mandres",
    "email": "mmandres9h@t-online.de"
  },
  {
    "firstname": "Kelby",
    "lastname": "Sinott",
    "email": "ksinott9i@ycombinator.com"
  },
  {
    "firstname": "Bea",
    "lastname": "Madoc-Jones",
    "email": "bmadocjones9j@blogtalkradio.com"
  },
  {
    "firstname": "Neil",
    "lastname": "Crate",
    "email": "ncrate9k@bbc.co.uk"
  },
  {
    "firstname": "Rhianon",
    "lastname": "Easterbrook",
    "email": "reasterbrook9l@creativecommons.org"
  },
  {
    "firstname": "Faber",
    "lastname": "Olek",
    "email": "folek9m@purevolume.com"
  },
  {
    "firstname": "Rici",
    "lastname": "Burnip",
    "email": "rburnip9n@cnn.com"
  },
  {
    "firstname": "Kaylil",
    "lastname": "Croker",
    "email": "kcroker9o@ocn.ne.jp"
  },
  {
    "firstname": "Jerry",
    "lastname": "Avrahamy",
    "email": "javrahamy9p@hubpages.com"
  },
  {
    "firstname": "Northrop",
    "lastname": "Kirmond",
    "email": "nkirmond9q@abc.net.au"
  },
  {
    "firstname": "Huberto",
    "lastname": "Gypps",
    "email": "hgypps9r@linkedin.com"
  },
  {
    "firstname": "Inglis",
    "lastname": "Vercruysse",
    "email": "ivercruysse9s@forbes.com"
  },
  {
    "firstname": "Griswold",
    "lastname": "Nacci",
    "email": "gnacci9t@newsvine.com"
  },
  {
    "firstname": "Andree",
    "lastname": "Fraulo",
    "email": "afraulo9u@blinklist.com"
  },
  {
    "firstname": "Dar",
    "lastname": "Oldacres",
    "email": "doldacres9v@last.fm"
  },
  {
    "firstname": "Lynea",
    "lastname": "Seedull",
    "email": "lseedull9w@slashdot.org"
  },
  {
    "firstname": "Tabbi",
    "lastname": "Rooper",
    "email": "trooper9x@indiegogo.com"
  },
  {
    "firstname": "Lennie",
    "lastname": "Saterthwait",
    "email": "lsaterthwait9y@yahoo.co.jp"
  },
  {
    "firstname": "Kristoffer",
    "lastname": "Dullard",
    "email": "kdullard9z@microsoft.com"
  },
  {
    "firstname": "Moselle",
    "lastname": "Jeffryes",
    "email": "mjeffryesa0@dell.com"
  },
  {
    "firstname": "Aubine",
    "lastname": "Raubenheimer",
    "email": "araubenheimera1@go.com"
  },
  {
    "firstname": "Afton",
    "lastname": "Brimman",
    "email": "abrimmana2@squidoo.com"
  },
  {
    "firstname": "Ronni",
    "lastname": "Legion",
    "email": "rlegiona3@4shared.com"
  },
  {
    "firstname": "Morrie",
    "lastname": "Hrycek",
    "email": "mhryceka4@liveinternet.ru"
  },
  {
    "firstname": "Kata",
    "lastname": "Haestier",
    "email": "khaestiera5@microsoft.com"
  },
  {
    "firstname": "Allegra",
    "lastname": "Whall",
    "email": "awhalla6@edublogs.org"
  },
  {
    "firstname": "Deidre",
    "lastname": "Bediss",
    "email": "dbedissa7@comsenz.com"
  },
  {
    "firstname": "Gail",
    "lastname": "Vallis",
    "email": "gvallisa8@networkadvertising.org"
  },
  {
    "firstname": "Kelley",
    "lastname": "Bromfield",
    "email": "kbromfielda9@harvard.edu"
  },
  {
    "firstname": "Delmer",
    "lastname": "Koppelmann",
    "email": "dkoppelmannaa@fda.gov"
  },
  {
    "firstname": "Gloriane",
    "lastname": "Bednell",
    "email": "gbednellab@infoseek.co.jp"
  },
  {
    "firstname": "Cherianne",
    "lastname": "Lintot",
    "email": "clintotac@ebay.com"
  },
  {
    "firstname": "Vinita",
    "lastname": "Grigoire",
    "email": "vgrigoiread@amazon.com"
  },
  {
    "firstname": "Winthrop",
    "lastname": "Gouldeby",
    "email": "wgouldebyae@chronoengine.com"
  },
  {
    "firstname": "Bryn",
    "lastname": "Blanko",
    "email": "bblankoaf@dell.com"
  },
  {
    "firstname": "Drusilla",
    "lastname": "Klimontovich",
    "email": "dklimontovichag@blogger.com"
  },
  {
    "firstname": "Tabitha",
    "lastname": "Brasner",
    "email": "tbrasnerah@accuweather.com"
  },
  {
    "firstname": "Rich",
    "lastname": "Canto",
    "email": "rcantoai@mapquest.com"
  },
  {
    "firstname": "Cammy",
    "lastname": "Izaac",
    "email": "cizaacaj@nps.gov"
  },
  {
    "firstname": "Susanne",
    "lastname": "Anthonsen",
    "email": "santhonsenak@businesswire.com"
  },
  {
    "firstname": "Nicolas",
    "lastname": "Cooke",
    "email": "ncookeal@tinyurl.com"
  },
  {
    "firstname": "Chan",
    "lastname": "Newbold",
    "email": "cnewboldam@japanpost.jp"
  },
  {
    "firstname": "Tobit",
    "lastname": "Merwe",
    "email": "tmerwean@accuweather.com"
  },
  {
    "firstname": "Alexandr",
    "lastname": "Faudrie",
    "email": "afaudrieao@chicagotribune.com"
  },
  {
    "firstname": "Evvy",
    "lastname": "Hedgeman",
    "email": "ehedgemanap@ovh.net"
  },
  {
    "firstname": "Cheryl",
    "lastname": "Mearing",
    "email": "cmearingaq@google.com.br"
  },
  {
    "firstname": "Lynna",
    "lastname": "Burnett",
    "email": "lburnettar@goodreads.com"
  },
  {
    "firstname": "Darcy",
    "lastname": "Aldritt",
    "email": "daldrittas@odnoklassniki.ru"
  },
  {
    "firstname": "Temple",
    "lastname": "McCrae",
    "email": "tmccraeat@usgs.gov"
  },
  {
    "firstname": "Harp",
    "lastname": "Rubbert",
    "email": "hrubbertau@skyrock.com"
  },
  {
    "firstname": "Kacie",
    "lastname": "Garken",
    "email": "kgarkenav@mac.com"
  },
  {
    "firstname": "Mattie",
    "lastname": "Saveall",
    "email": "msaveallaw@naver.com"
  },
  {
    "firstname": "Lura",
    "lastname": "Timson",
    "email": "ltimsonax@canalblog.com"
  },
  {
    "firstname": "Clayborne",
    "lastname": "Egginton",
    "email": "ceggintonay@fda.gov"
  },
  {
    "firstname": "Nettle",
    "lastname": "Glasgow",
    "email": "nglasgowaz@goodreads.com"
  },
  {
    "firstname": "Rainer",
    "lastname": "Ropkes",
    "email": "rropkesb0@istockphoto.com"
  },
  {
    "firstname": "Emeline",
    "lastname": "Foulks",
    "email": "efoulksb1@cbc.ca"
  },
  {
    "firstname": "Giulio",
    "lastname": "Misson",
    "email": "gmissonb2@wikispaces.com"
  },
  {
    "firstname": "Elijah",
    "lastname": "Balnaves",
    "email": "ebalnavesb3@dion.ne.jp"
  },
  {
    "firstname": "Anestassia",
    "lastname": "Lowis",
    "email": "alowisb4@cbsnews.com"
  },
  {
    "firstname": "Malcolm",
    "lastname": "Johnigan",
    "email": "mjohniganb5@is.gd"
  },
  {
    "firstname": "Ryan",
    "lastname": "Braidford",
    "email": "rbraidfordb6@bloglovin.com"
  },
  {
    "firstname": "Chauncey",
    "lastname": "Bernardt",
    "email": "cbernardtb7@msn.com"
  },
  {
    "firstname": "Faustine",
    "lastname": "Drover",
    "email": "fdroverb8@cloudflare.com"
  },
  {
    "firstname": "Lori",
    "lastname": "Kinnon",
    "email": "lkinnonb9@wikimedia.org"
  },
  {
    "firstname": "Malissia",
    "lastname": "Eathorne",
    "email": "meathorneba@xing.com"
  },
  {
    "firstname": "Marybeth",
    "lastname": "Toffanini",
    "email": "mtoffaninibb@huffingtonpost.com"
  },
  {
    "firstname": "Merrilee",
    "lastname": "Francklin",
    "email": "mfrancklinbc@stanford.edu"
  },
  {
    "firstname": "Giacopo",
    "lastname": "Vine",
    "email": "gvinebd@bing.com"
  },
  {
    "firstname": "Lark",
    "lastname": "Arlott",
    "email": "larlottbe@auda.org.au"
  },
  {
    "firstname": "Rockey",
    "lastname": "Lowery",
    "email": "rlowerybf@comsenz.com"
  },
  {
    "firstname": "Minny",
    "lastname": "Newdick",
    "email": "mnewdickbg@wordpress.com"
  },
  {
    "firstname": "Twila",
    "lastname": "Nitti",
    "email": "tnittibh@google.cn"
  },
  {
    "firstname": "Korrie",
    "lastname": "Burker",
    "email": "kburkerbi@techcrunch.com"
  },
  {
    "firstname": "Loleta",
    "lastname": "Thornbarrow",
    "email": "lthornbarrowbj@omniture.com"
  },
  {
    "firstname": "Pierre",
    "lastname": "Persian",
    "email": "ppersianbk@google.de"
  },
  {
    "firstname": "Fiann",
    "lastname": "Artharg",
    "email": "farthargbl@ocn.ne.jp"
  },
  {
    "firstname": "Duke",
    "lastname": "Sussans",
    "email": "dsussansbm@yellowpages.com"
  },
  {
    "firstname": "Clayborn",
    "lastname": "Fleetham",
    "email": "cfleethambn@netscape.com"
  },
  {
    "firstname": "Lek",
    "lastname": "Cornford",
    "email": "lcornfordbo@newyorker.com"
  },
  {
    "firstname": "Carolann",
    "lastname": "Guilbert",
    "email": "cguilbertbp@nhs.uk"
  },
  {
    "firstname": "Desirae",
    "lastname": "Saffon",
    "email": "dsaffonbq@is.gd"
  },
  {
    "firstname": "Ronda",
    "lastname": "Scarratt",
    "email": "rscarrattbr@bluehost.com"
  },
  {
    "firstname": "Jareb",
    "lastname": "Spragge",
    "email": "jspraggebs@newyorker.com"
  },
  {
    "firstname": "Putnam",
    "lastname": "Hayer",
    "email": "phayerbt@indiegogo.com"
  },
  {
    "firstname": "Stepha",
    "lastname": "Shevill",
    "email": "sshevillbu@un.org"
  },
  {
    "firstname": "Isis",
    "lastname": "Winterborne",
    "email": "iwinterbornebv@webmd.com"
  },
  {
    "firstname": "Bryant",
    "lastname": "Wallace",
    "email": "bwallacebw@epa.gov"
  },
  {
    "firstname": "Mohammed",
    "lastname": "Alban",
    "email": "malbanbx@ow.ly"
  },
  {
    "firstname": "Ollie",
    "lastname": "Groundwater",
    "email": "ogroundwaterby@artisteer.com"
  },
  {
    "firstname": "Marylinda",
    "lastname": "Behnen",
    "email": "mbehnenbz@tinyurl.com"
  },
  {
    "firstname": "Arte",
    "lastname": "Phillot",
    "email": "aphillotc0@lycos.com"
  },
  {
    "firstname": "Boycey",
    "lastname": "Trewett",
    "email": "btrewettc1@wired.com"
  },
  {
    "firstname": "Curt",
    "lastname": "Haffenden",
    "email": "chaffendenc2@harvard.edu"
  },
  {
    "firstname": "Ruprecht",
    "lastname": "Nelmes",
    "email": "rnelmesc3@illinois.edu"
  },
  {
    "firstname": "Lolita",
    "lastname": "Pidgeon",
    "email": "lpidgeonc4@amazon.com"
  },
  {
    "firstname": "Fayth",
    "lastname": "Crosland",
    "email": "fcroslandc5@narod.ru"
  },
  {
    "firstname": "Micky",
    "lastname": "Spurryer",
    "email": "mspurryerc6@engadget.com"
  },
  {
    "firstname": "Shandie",
    "lastname": "Springham",
    "email": "sspringhamc7@geocities.jp"
  },
  {
    "firstname": "Vere",
    "lastname": "Vasyatkin",
    "email": "vvasyatkinc8@washingtonpost.com"
  },
  {
    "firstname": "Freddie",
    "lastname": "Parrett",
    "email": "fparrettc9@desdev.cn"
  },
  {
    "firstname": "Violetta",
    "lastname": "Hammel",
    "email": "vhammelca@bluehost.com"
  },
  {
    "firstname": "Jackie",
    "lastname": "Bradlaugh",
    "email": "jbradlaughcb@dyndns.org"
  },
  {
    "firstname": "Quincey",
    "lastname": "Balderston",
    "email": "qbalderstoncc@last.fm"
  },
  {
    "firstname": "Nappie",
    "lastname": "Holwell",
    "email": "nholwellcd@nps.gov"
  },
  {
    "firstname": "Rhodie",
    "lastname": "Dust",
    "email": "rdustce@nsw.gov.au"
  },
  {
    "firstname": "Wainwright",
    "lastname": "McKane",
    "email": "wmckanecf@vkontakte.ru"
  },
  {
    "firstname": "Lauren",
    "lastname": "Dimitrescu",
    "email": "ldimitrescucg@utexas.edu"
  },
  {
    "firstname": "Allie",
    "lastname": "Very",
    "email": "averych@hugedomains.com"
  },
  {
    "firstname": "Haskell",
    "lastname": "Richardin",
    "email": "hrichardinci@apple.com"
  },
  {
    "firstname": "Roby",
    "lastname": "Dineen",
    "email": "rdineencj@cmu.edu"
  },
  {
    "firstname": "Lorrie",
    "lastname": "De Freyne",
    "email": "ldefreyneck@youtube.com"
  },
  {
    "firstname": "Dionisio",
    "lastname": "Poytheras",
    "email": "dpoytherascl@nymag.com"
  },
  {
    "firstname": "Alick",
    "lastname": "Grundell",
    "email": "agrundellcm@wordpress.org"
  },
  {
    "firstname": "Mariquilla",
    "lastname": "Bevans",
    "email": "mbevanscn@dailymail.co.uk"
  },
  {
    "firstname": "Brigg",
    "lastname": "Millmoe",
    "email": "bmillmoeco@sciencedirect.com"
  },
  {
    "firstname": "Romy",
    "lastname": "Anthony",
    "email": "ranthonycp@hud.gov"
  },
  {
    "firstname": "Breena",
    "lastname": "Penhearow",
    "email": "bpenhearowcq@eepurl.com"
  },
  {
    "firstname": "Rolando",
    "lastname": "Millgate",
    "email": "rmillgatecr@123-reg.co.uk"
  },
  {
    "firstname": "Hayyim",
    "lastname": "Shakesby",
    "email": "hshakesbycs@answers.com"
  },
  {
    "firstname": "Mickie",
    "lastname": "Kempshall",
    "email": "mkempshallct@chicagotribune.com"
  },
  {
    "firstname": "Justis",
    "lastname": "Karchewski",
    "email": "jkarchewskicu@deliciousdays.com"
  },
  {
    "firstname": "Karlyn",
    "lastname": "Vankin",
    "email": "kvankincv@upenn.edu"
  },
  {
    "firstname": "Art",
    "lastname": "Claypole",
    "email": "aclaypolecw@miitbeian.gov.cn"
  },
  {
    "firstname": "Nevins",
    "lastname": "Rubberts",
    "email": "nrubbertscx@simplemachines.org"
  },
  {
    "firstname": "Saunderson",
    "lastname": "Eby",
    "email": "sebycy@artisteer.com"
  },
  {
    "firstname": "Brandea",
    "lastname": "Zanussii",
    "email": "bzanussiicz@imgur.com"
  },
  {
    "firstname": "Frasco",
    "lastname": "Colter",
    "email": "fcolterd0@bbc.co.uk"
  },
  {
    "firstname": "Eugen",
    "lastname": "Edds",
    "email": "eeddsd1@weebly.com"
  },
  {
    "firstname": "Lynde",
    "lastname": "Elcombe",
    "email": "lelcombed2@networkadvertising.org"
  },
  {
    "firstname": "Abe",
    "lastname": "Challenor",
    "email": "achallenord3@weibo.com"
  },
  {
    "firstname": "Marleen",
    "lastname": "Gorling",
    "email": "mgorlingd4@washington.edu"
  },
  {
    "firstname": "Orbadiah",
    "lastname": "Macura",
    "email": "omacurad5@hp.com"
  },
  {
    "firstname": "Dottie",
    "lastname": "Celand",
    "email": "dcelandd6@earthlink.net"
  },
  {
    "firstname": "Fons",
    "lastname": "Widdows",
    "email": "fwiddowsd7@discuz.net"
  },
  {
    "firstname": "Alair",
    "lastname": "Arlow",
    "email": "aarlowd8@ucoz.ru"
  },
  {
    "firstname": "Guinevere",
    "lastname": "Chansonne",
    "email": "gchansonned9@livejournal.com"
  },
  {
    "firstname": "Jojo",
    "lastname": "Landon",
    "email": "jlandonda@amazon.co.uk"
  },
  {
    "firstname": "Parrnell",
    "lastname": "Luchelli",
    "email": "pluchellidb@cargocollective.com"
  },
  {
    "firstname": "Kirsten",
    "lastname": "Fury",
    "email": "kfurydc@usda.gov"
  },
  {
    "firstname": "Robinet",
    "lastname": "Fuente",
    "email": "rfuentedd@vk.com"
  },
  {
    "firstname": "Aili",
    "lastname": "MacAirt",
    "email": "amacairtde@hp.com"
  },
  {
    "firstname": "Lisetta",
    "lastname": "La Batie",
    "email": "llabatiedf@de.vu"
  },
  {
    "firstname": "Jobey",
    "lastname": "Aldrich",
    "email": "jaldrichdg@1688.com"
  },
  {
    "firstname": "Wilie",
    "lastname": "Verrick",
    "email": "wverrickdh@oracle.com"
  },
  {
    "firstname": "Bail",
    "lastname": "Malpass",
    "email": "bmalpassdi@myspace.com"
  },
  {
    "firstname": "Bibbie",
    "lastname": "Kyston",
    "email": "bkystondj@jugem.jp"
  },
  {
    "firstname": "Viviyan",
    "lastname": "Gatesman",
    "email": "vgatesmandk@nature.com"
  },
  {
    "firstname": "Devinne",
    "lastname": "Raitt",
    "email": "draittdl@macromedia.com"
  },
  {
    "firstname": "Deeann",
    "lastname": "Symon",
    "email": "dsymondm@epa.gov"
  },
  {
    "firstname": "Cassi",
    "lastname": "Dance",
    "email": "cdancedn@biblegateway.com"
  },
  {
    "firstname": "Masha",
    "lastname": "Clinnick",
    "email": "mclinnickdo@unicef.org"
  },
  {
    "firstname": "Carry",
    "lastname": "Winfield",
    "email": "cwinfielddp@ox.ac.uk"
  },
  {
    "firstname": "Jon",
    "lastname": "Jepson",
    "email": "jjepsondq@google.nl"
  },
  {
    "firstname": "Ramsey",
    "lastname": "Barnes",
    "email": "rbarnesdr@macromedia.com"
  },
  {
    "firstname": "Alaster",
    "lastname": "Cavanaugh",
    "email": "acavanaughds@smugmug.com"
  },
  {
    "firstname": "Amelie",
    "lastname": "Casini",
    "email": "acasinidt@tumblr.com"
  },
  {
    "firstname": "Brynn",
    "lastname": "Mabone",
    "email": "bmabonedu@blogs.com"
  },
  {
    "firstname": "Fabian",
    "lastname": "Lorinez",
    "email": "florinezdv@cdc.gov"
  }
]